{
  "id": "fixture-hobby-pickleball",
  "name": "Pickleball",
  "notes": "Casual games at the local courts.",
  "tasks": [
    {
      "id": "fixture-hobby-pickleball-play",
      "label": "Play pickleball",
      "typicalTimeMinutes": 90,
      "occurrence": {
        "kind": "weekly",
        "days": ["Sat"],
        "timeOfDay": "morning"
      },
      "completions": []
    },
    {
      "id": "fixture-hobby-pickleball-restring",
      "label": "Replace paddle grip",
      "typicalTimeMinutes": 20,
      "occurrence": { "kind": "oneoff" },
      "completions": []
    }
  ],
  "createdAt": "2026-05-01T12:00:00.000Z",
  "updatedAt": "2026-05-01T12:00:00.000Z"
}
